caikit_compose/__init__.py
caikit_compose/_version.py
caikit_compose/message.py
caikit_compose/version.py
caikit_compose/actors/__init__.py
caikit_compose/actors/base.py
caikit_compose/actors/model_actor.py
caikit_compose/group_store/__init__.py
caikit_compose/group_store/base.py
caikit_compose/group_store/factory.py
caikit_compose/group_store/local.py
caikit_compose/grouping/__init__.py
caikit_compose/grouping/base.py
caikit_compose/grouping/compound_grouping_base.py
caikit_compose/grouping/count_grouping.py
caikit_compose/grouping/factory.py
caikit_compose/grouping/individual_grouping.py
caikit_compose/grouping/key_grouping.py
caikit_compose/grouping/subscription_manager.py
caikit_compose/message_queue/__init__.py
caikit_compose/message_queue/base.py
caikit_compose/message_queue/factory.py
caikit_compose/message_queue/local.py
caikit_compose/utils/__init__.py
caikit_compose/utils/dict_tools.py
caikit_compose-0.1.0.dist-info/LICENSE
caikit_compose-0.1.0.dist-info/METADATA
caikit_compose-0.1.0.dist-info/WHEEL
caikit_compose-0.1.0.dist-info/top_level.txt
caikit_compose-0.1.0.dist-info/RECORD
