Metadata-Version: 2.1
Name: caikit-compose
Version: 0.1.0
Summary: Dynamic composition framework for caikit modules
License: Apache-2.0
Classifier: License :: OSI Approved :: Apache Software License
Requires-Python: >=3.11
License-File: LICENSE
Requires-Dist: caikit<0.26,>=0.25
Provides-Extra: dev-test
Requires-Dist: pytest-cov<5.0,>=2.10.1; extra == "dev-test"
Requires-Dist: pytest-html<5.0,>=3.1.1; extra == "dev-test"
Requires-Dist: pytest<8.0,>=6.2.5; extra == "dev-test"
Requires-Dist: wheel>=0.38.4; extra == "dev-test"
Provides-Extra: dev-fmt
Requires-Dist: ruff==0.1.7; extra == "dev-fmt"
Requires-Dist: pre-commit<4.0,>=3.0.4; extra == "dev-fmt"
Requires-Dist: pydeps<2,>=1.12.12; extra == "dev-fmt"
Provides-Extra: all-dev
Requires-Dist: caikit-compose[dev-fmt,dev-test]; extra == "all-dev"
